.hgignore
.installed.cfg
.project
.pydevproject
LICENSE
MANIFEST.in
README.txt
bootstrap.py
buildout.cfg
setup.py
docs/HISTORY.txt
docs/README.txt
src/ztfy/__init__.py
src/ztfy.workflow.egg-info/PKG-INFO
src/ztfy.workflow.egg-info/SOURCES.txt
src/ztfy.workflow.egg-info/dependency_links.txt
src/ztfy.workflow.egg-info/entry_points.txt
src/ztfy.workflow.egg-info/namespace_packages.txt
src/ztfy.workflow.egg-info/not-zip-safe
src/ztfy.workflow.egg-info/requires.txt
src/ztfy.workflow.egg-info/top_level.txt
src/ztfy/workflow/README.txt
src/ztfy/workflow/__init__.py
src/ztfy/workflow/configure.zcml
src/ztfy/workflow/content.py
src/ztfy/workflow/database.py
src/ztfy/workflow/events.py
src/ztfy/workflow/interfaces.py
src/ztfy/workflow/versions.py
src/ztfy/workflow/vocabulary.py
src/ztfy/workflow/workflow.py
src/ztfy/workflow/browser/__init__.py
src/ztfy/workflow/browser/configure.zcml
src/ztfy/workflow/browser/namespace.py
src/ztfy/workflow/browser/viewlet/__init__.py
src/ztfy/workflow/browser/viewlet/configure.zcml
src/ztfy/workflow/browser/viewlet/interfaces.py
src/ztfy/workflow/browser/viewlet/transitions.pt
src/ztfy/workflow/doctests/README.txt
src/ztfy/workflow/locales/ztfy.workflow.pot
src/ztfy/workflow/locales/en/LC_MESSAGES/ztfy.workflow.mo
src/ztfy/workflow/locales/en/LC_MESSAGES/ztfy.workflow.po
src/ztfy/workflow/locales/fr/LC_MESSAGES/ztfy.workflow.mo
src/ztfy/workflow/locales/fr/LC_MESSAGES/ztfy.workflow.po
src/ztfy/workflow/tal/__init__.py
src/ztfy/workflow/tal/api.py
src/ztfy/workflow/tal/configure.zcml
src/ztfy/workflow/tal/interfaces.py
src/ztfy/workflow/tests/__init__.py
src/ztfy/workflow/tests/test_workflowdocs.py
src/ztfy/workflow/tests/test_workflowdocstrings.py